{"targets": [{"isStage": true, "name": "Stage", "variables": {"`jEk@4|i[#Fk?(8x)AV.-my variable": ["my variable", 0]}, "lists": {}, "broadcasts": {}, "blocks": {}, "comments": {}, "currentCostume": 1, "costumes": [{"assetId": "ceaaf7d0944f3819171dc4393d0afc0b", "name": "backdrop3", "bitmapResolution": 1, "md5ext": "ceaaf7d0944f3819171dc4393d0afc0b.svg", "dataFormat": "svg", "rotationCenterX": 203.25, "rotationCenterY": 143.1862711111109}, {"assetId": "cd21514d0531fdffb22204e0ec5ed84a", "name": "backdrop1", "bitmapResolution": 1, "md5ext": "cd21514d0531fdffb22204e0ec5ed84a.svg", "dataFormat": "svg", "rotationCenterX": 0, "rotationCenterY": 0}, {"assetId": "1e323c103a11954d4984d45516b95369", "name": "Screenshot 2019-03-20 at 9", "bitmapResolution": 1, "md5ext": "1e323c103a11954d4984d45516b95369.svg", "dataFormat": "svg", "rotationCenterX": 240, "rotationCenterY": 181.49999999999983}, {"assetId": "cd21514d0531fdffb22204e0ec5ed84a", "name": "backdrop2", "bitmapResolution": 1, "md5ext": "cd21514d0531fdffb22204e0ec5ed84a.svg", "dataFormat": "svg", "rotationCenterX": 0, "rotationCenterY": 0}, {"assetId": "3f015811f947426b8b889cd2f204ddf5", "name": "cat", "bitmapResolution": 1, "md5ext": "3f015811f947426b8b889cd2f204ddf5.svg", "dataFormat": "svg", "rotationCenterX": 133.5, "rotationCenterY": 151}, {"assetId": "cd21514d0531fdffb22204e0ec5ed84a", "name": "backdrop4", "bitmapResolution": 1, "md5ext": "cd21514d0531fdffb22204e0ec5ed84a.svg", "dataFormat": "svg", "rotationCenterX": 0, "rotationCenterY": 0}, {"assetId": "db899660d8cc9bbe08b09d5e80e0493a", "name": "backdrop5", "bitmapResolution": 1, "md5ext": "db899660d8cc9bbe08b09d5e80e0493a.svg", "dataFormat": "svg", "rotationCenterX": 311.5508561965794, "rotationCenterY": 252.9061279296875}], "sounds": [{"assetId": "83a9787d4cb6f3b7632b4ddfebf74367", "name": "pop", "dataFormat": "wav", "format": "", "rate": 48000, "sampleCount": 1123, "md5ext": "83a9787d4cb6f3b7632b4ddfebf74367.wav"}], "volume": 100, "layerOrder": 0, "tempo": 60, "videoTransparency": 50, "videoState": "on", "textToSpeechLanguage": null}, {"isStage": false, "name": "mouse", "variables": {}, "lists": {}, "broadcasts": {}, "blocks": {"IZ#dlj[}$#jitCs%M/E{": {"opcode": "event_whenflagclicked", "next": "vU`40j63]o,bzR{Dr+sz", "parent": null, "inputs": {}, "fields": {}, "shadow": false, "topLevel": true, "x": 192, "y": 136}, "G0WM^6DjFYB|3+`IHP+P": {"opcode": "looks_switchbackdropto", "next": "c3|@QxF%o)n$4~lw]c9T", "parent": "f26wZOpY-iy[Q1g:=S|!", "inputs": {"BACKDROP": [1, "!fq(1RDO65$_(sY5[*8V"]}, "fields": {}, "shadow": false, "topLevel": false}, "!fq(1RDO65$_(sY5[*8V": {"opcode": "looks_backdrops", "next": null, "parent": "G0WM^6DjFYB|3+`IHP+P", "inputs": {}, "fields": {"BACKDROP": ["backdrop1", null]}, "shadow": true, "topLevel": false}, "Y~FJeJ^z|s2rDFqsda0x": {"opcode": "control_forever", "next": null, "parent": "c3|@QxF%o)n$4~lw]c9T", "inputs": {"SUBSTACK": [2, "aApI`l(Yv1vnY!){G)e9"]}, "fields": {}, "shadow": false, "topLevel": false}, "aApI`l(Yv1vnY!){G)e9": {"opcode": "motion_goto", "next": null, "parent": "Y~FJeJ^z|s2rDFqsda0x", "inputs": {"TO": [1, "gl#!il2oC{Uu9EE)N6N5"]}, "fields": {}, "shadow": false, "topLevel": false}, "gl#!il2oC{Uu9EE)N6N5": {"opcode": "motion_goto_menu", "next": null, "parent": "aApI`l(Yv1vnY!){G)e9", "inputs": {}, "fields": {"TO": ["_mouse_", null]}, "shadow": true, "topLevel": false}, "vU`40j63]o,bzR{Dr+sz": {"opcode": "looks_hide", "next": "f26wZOpY-iy[Q1g:=S|!", "parent": "IZ#dlj[}$#jitCs%M/E{", "inputs": {}, "fields": {}, "shadow": false, "topLevel": false}, "f26wZOpY-iy[Q1g:=S|!": {"opcode": "control_wait", "next": "G0WM^6DjFYB|3+`IHP+P", "parent": "vU`40j63]o,bzR{Dr+sz", "inputs": {"DURATION": [1, [5, "3"]]}, "fields": {}, "shadow": false, "topLevel": false}, "c3|@QxF%o)n$4~lw]c9T": {"opcode": "looks_show", "next": "Y~FJeJ^z|s2rDFqsda0x", "parent": "G0WM^6DjFYB|3+`IHP+P", "inputs": {}, "fields": {}, "shadow": false, "topLevel": false}}, "comments": {}, "currentCostume": 0, "costumes": [{"assetId": "fc9d0b4764ca82d8ee1583be9d5251b2", "name": "mouse", "bitmapResolution": 1, "md5ext": "fc9d0b4764ca82d8ee1583be9d5251b2.svg", "dataFormat": "svg", "rotationCenterX": 34.965776724223474, "rotationCenterY": 27.508384813970935}], "sounds": [], "volume": 100, "layerOrder": 1, "visible": true, "x": -182, "y": 180, "size": 100, "direction": 90, "draggable": false, "rotationStyle": "all around"}, {"isStage": false, "name": "chrome", "variables": {}, "lists": {}, "broadcasts": {}, "blocks": {"x{GGGFnmf{G#*=U=AhBd": {"opcode": "event_whenthisspriteclicked", "next": "K3Q1JZj*WrWxld2^%v%_", "parent": null, "inputs": {}, "fields": {}, "shadow": false, "topLevel": true, "x": 169, "y": 67}, "K3Q1JZj*WrWxld2^%v%_": {"opcode": "looks_switchbackdropto", "next": null, "parent": "x{GGGFnmf{G#*=U=AhBd", "inputs": {"BACKDROP": [1, "mGnOF30q@{sB%!:XoaoN"]}, "fields": {}, "shadow": false, "topLevel": false}, "mGnOF30q@{sB%!:XoaoN": {"opcode": "looks_backdrops", "next": null, "parent": "K3Q1JZj*WrWxld2^%v%_", "inputs": {}, "fields": {"BACKDROP": ["backdrop3", null]}, "shadow": true, "topLevel": false}, "/s{)@hP#haD@aGWrC33@": {"opcode": "control_wait", "next": "8U;,AWGO,--amS#}3RG3", "parent": "zcTiAaAm6~GNbIq=MfEf", "inputs": {"DURATION": [1, [5, "3"]]}, "fields": {}, "shadow": false, "topLevel": false}, "zcTiAaAm6~GNbIq=MfEf": {"opcode": "looks_hide", "next": "/s{)@hP#haD@aGWrC33@", "parent": ",gH399GkSv;=EdBO4H-}", "inputs": {}, "fields": {}, "shadow": false, "topLevel": false}, "8U;,AWGO,--amS#}3RG3": {"opcode": "looks_show", "next": null, "parent": "/s{)@hP#haD@aGWrC33@", "inputs": {}, "fields": {}, "shadow": false, "topLevel": false}, ",gH399GkSv;=EdBO4H-}": {"opcode": "event_whenflagclicked", "next": "zcTiAaAm6~GNbIq=MfEf", "parent": null, "inputs": {}, "fields": {}, "shadow": false, "topLevel": true, "x": 379, "y": 297}}, "comments": {}, "currentCostume": 0, "costumes": [{"assetId": "601df2d40997f7006717d262ff34110f", "name": "chrome", "bitmapResolution": 1, "md5ext": "601df2d40997f7006717d262ff34110f.svg", "dataFormat": "svg", "rotationCenterX": -115.5, "rotationCenterY": 214.49999999999972}], "sounds": [], "volume": 100, "layerOrder": 2, "visible": true, "x": 66, "y": -36, "size": 100, "direction": 90, "draggable": false, "rotationStyle": "all around"}, {"isStage": false, "name": "Bell", "variables": {}, "lists": {}, "broadcasts": {}, "blocks": {"RGIWC!x759p+mZYgfh:0": {"opcode": "event_whenbackdropswitchesto", "next": "C1/F^Aev_n1|O}^K9CL`", "parent": null, "inputs": {}, "fields": {"BACKDROP": ["backdrop1", null]}, "shadow": false, "topLevel": true, "x": 28, "y": 50}, "C1/F^Aev_n1|O}^K9CL`": {"opcode": "looks_hide", "next": null, "parent": "RGIWC!x759p+mZYgfh:0", "inputs": {}, "fields": {}, "shadow": false, "topLevel": false}, "6ayZ]5,$;Opfm-0[8=hC": {"opcode": "event_whenbackdropswitchesto", "next": "!EJ0SM.DB;UgNq1Y5-Yq", "parent": null, "inputs": {}, "fields": {"BACKDROP": ["backdrop3", null]}, "shadow": false, "topLevel": true, "x": 38, "y": 251}, "!EJ0SM.DB;UgNq1Y5-Yq": {"opcode": "looks_show", "next": null, "parent": "6ayZ]5,$;Opfm-0[8=hC", "inputs": {}, "fields": {}, "shadow": false, "topLevel": false}, "I!Hm[w9%,m#OBp-IB+}`": {"opcode": "event_whenbackdropswitchesto", "next": "y1/t[lnDl*QfshT|8_4V", "parent": null, "inputs": {}, "fields": {"BACKDROP": ["Screenshot 2019-03-20 at 9", null]}, "shadow": false, "topLevel": true, "x": 53, "y": 441}, "y1/t[lnDl*QfshT|8_4V": {"opcode": "looks_hide", "next": null, "parent": "I!Hm[w9%,m#OBp-IB+}`", "inputs": {}, "fields": {}, "shadow": false, "topLevel": false}, "$%e;zKk2q~!sa,x0DlO,": {"opcode": "event_whenthisspriteclicked", "next": "=M]7g@,6.6DO)fc69]1F", "parent": null, "inputs": {}, "fields": {}, "shadow": false, "topLevel": true, "x": 511, "y": 76}, "=M]7g@,6.6DO)fc69]1F": {"opcode": "sound_playuntildone", "next": "fyA{bRt:Y,Y8bRbsUBcA", "parent": "$%e;zKk2q~!sa,x0DlO,", "inputs": {"SOUND_MENU": [1, "WSXUu9mEw@wZ!bz7.)w@"]}, "fields": {}, "shadow": false, "topLevel": false}, "WSXUu9mEw@wZ!bz7.)w@": {"opcode": "sound_sounds_menu", "next": null, "parent": "=M]7g@,6.6DO)fc69]1F", "inputs": {}, "fields": {"SOUND_MENU": ["bell toll", null]}, "shadow": true, "topLevel": false}, "fyA{bRt:Y,Y8bRbsUBcA": {"opcode": "looks_switchbackdropto", "next": "6ymaMM[vu7)$BMD`ffr^", "parent": "=M]7g@,6.6DO)fc69]1F", "inputs": {"BACKDROP": [1, "(i|XSN!`b.,D7^]70t`}"]}, "fields": {}, "shadow": false, "topLevel": false}, "(i|XSN!`b.,D7^]70t`}": {"opcode": "looks_backdrops", "next": null, "parent": "fyA{bRt:Y,Y8bRbsUBcA", "inputs": {}, "fields": {"BACKDROP": ["Screenshot 2019-03-20 at 9", null]}, "shadow": true, "topLevel": false}, "6ymaMM[vu7)$BMD`ffr^": {"opcode": "control_wait", "next": "/y1R8.#f9Z%i2Ih%gLNy", "parent": "fyA{bRt:Y,Y8bRbsUBcA", "inputs": {"DURATION": [1, [5, "5"]]}, "fields": {}, "shadow": false, "topLevel": false}, "/y1R8.#f9Z%i2Ih%gLNy": {"opcode": "looks_switchbackdropto", "next": null, "parent": "6ymaMM[vu7)$BMD`ffr^", "inputs": {"BACKDROP": [1, "=^:]@1{bh^HWHQQQWD?6"]}, "fields": {}, "shadow": false, "topLevel": false}, "=^:]@1{bh^HWHQQQWD?6": {"opcode": "looks_backdrops", "next": null, "parent": "/y1R8.#f9Z%i2Ih%gLNy", "inputs": {}, "fields": {"BACKDROP": ["cat", null]}, "shadow": true, "topLevel": false}}, "comments": {}, "currentCostume": 0, "costumes": [{"assetId": "8c0234fe1bfd36f5a72e975fbbc18bfd", "name": "bell1", "bitmapResolution": 1, "md5ext": "8c0234fe1bfd36f5a72e975fbbc18bfd.svg", "dataFormat": "svg", "rotationCenterX": 59, "rotationCenterY": 69}], "sounds": [{"assetId": "25d61e79cbeba4041eebeaebd7bf9598", "name": "bell toll", "dataFormat": "wav", "format": "", "rate": 48000, "sampleCount": 196649, "md5ext": "25d61e79cbeba4041eebeaebd7bf9598.wav"}], "volume": 100, "layerOrder": 3, "visible": false, "x": -170, "y": -152, "size": 100, "direction": 90, "draggable": false, "rotationStyle": "all around"}, {"isStage": false, "name": "Scratch_Solo", "variables": {}, "lists": {}, "broadcasts": {}, "blocks": {"7wi2c;HzTMlX$MRgI1M6": {"opcode": "event_whenflagclicked", "next": "hbwrIv4i{pX}[;~AHy5X", "parent": null, "inputs": {}, "fields": {}, "shadow": false, "topLevel": true, "x": 200, "y": 105}, "@TN#7_@Q#8(I0;(Dm#~B": {"opcode": "control_wait", "next": "a}F9@,ZZSRD$]f0SeKaw", "parent": "C3.rzCifNI0G##N8cxW.", "inputs": {"DURATION": [1, [5, "2"]]}, "fields": {}, "shadow": false, "topLevel": false}, "C3.rzCifNI0G##N8cxW.": {"opcode": "looks_show", "next": "@TN#7_@Q#8(I0;(Dm#~B", "parent": "5$_j^b^L`H[`Nb:A1!k1", "inputs": {}, "fields": {}, "shadow": false, "topLevel": false}, "a}F9@,ZZSRD$]f0SeKaw": {"opcode": "looks_setsizeto", "next": "qROD^IZA|/-Z]Avk2$fO", "parent": "@TN#7_@Q#8(I0;(Dm#~B", "inputs": {"SIZE": [1, [4, "25"]]}, "fields": {}, "shadow": false, "topLevel": false}, "qROD^IZA|/-Z]Avk2$fO": {"opcode": "motion_gotoxy", "next": null, "parent": "a}F9@,ZZSRD$]f0SeKaw", "inputs": {"X": [1, [4, "197"]], "Y": [1, [4, "-135"]]}, "fields": {}, "shadow": false, "topLevel": false}, "5$_j^b^L`H[`Nb:A1!k1": {"opcode": "looks_setsizeto", "next": "C3.rzCifNI0G##N8cxW.", "parent": "hbwrIv4i{pX}[;~AHy5X", "inputs": {"SIZE": [1, [4, "100"]]}, "fields": {}, "shadow": false, "topLevel": false}, "hbwrIv4i{pX}[;~AHy5X": {"opcode": "motion_glidesecstoxy", "next": "5$_j^b^L`H[`Nb:A1!k1", "parent": "7wi2c;HzTMlX$MRgI1M6", "inputs": {"SECS": [1, [4, "1"]], "X": [1, [4, "-12"]], "Y": [1, [4, "0"]]}, "fields": {}, "shadow": false, "topLevel": false}}, "comments": {}, "currentCostume": 0, "costumes": [{"assetId": "1d2669766da09e530b715051a532b3bd", "name": "Scratch_Solo", "bitmapResolution": 2, "md5ext": "1d2669766da09e530b715051a532b3bd.png", "dataFormat": "png", "rotationCenterX": 299.5, "rotationCenterY": 360}], "sounds": [], "volume": 100, "layerOrder": 4, "visible": true, "x": 197, "y": -135, "size": 25, "direction": 90, "draggable": false, "rotationStyle": "all around"}], "monitors": [], "extensions": [], "meta": {"semver": "3.0.0", "vm": "0.2.0-prerelease.20190321151527", "agent": "Mozilla/5.0 (X11; CrOS aarch64 11316.165.0) AppleWebKit/537.36 (KHTML, like Gecko) Chrome/72.0.3626.122 Safari/537.36"}}